README
flask_dbkit.py
setup.cfg
setup.py
Flask_DBKit.egg-info/PKG-INFO
Flask_DBKit.egg-info/SOURCES.txt
Flask_DBKit.egg-info/dependency_links.txt
Flask_DBKit.egg-info/not-zip-safe
Flask_DBKit.egg-info/requires.txt
Flask_DBKit.egg-info/top_level.txt