Metadata-Version: 1.1
Name: Flask-DBKit
Version: 0.0.1
Summary: dbkit integration for Flask.
Home-page: https://github.com/justinfay/flask-dbkit
Author: Justin Fay
Author-email: mail@justinfay.me
License: BSD
Platform: any
Classifier: Development Status :: 4 - Beta
Classifier: Environment :: Web Environment
Classifier: Intended Audience :: Developers
Classifier: License :: OSI Approved :: BSD License
Classifier: Operating System :: OS Independent
Classifier: Programming Language :: Python
Classifier: Topic :: Internet :: WWW/HTTP :: Dynamic Content
Classifier: Topic :: Software Development :: Libraries :: Python Modules
